dnastorage/__init__.py
dnastorage/exceptions.py
dnastorage/codec/__init__.py
dnastorage/codec/base_codec.py
dnastorage/codec/base_conversion.py
dnastorage/codec/binary.py
dnastorage/codec/block.py
dnastorage/codec/builder.py
dnastorage/codec/codecfile.py
dnastorage/codec/commafreecodec.py
dnastorage/codec/dense.py
dnastorage/codec/huffman.py
dnastorage/codec/huffman_table.py
dnastorage/codec/layered.py
dnastorage/codec/phys.py
dnastorage/codec/strand.py
dnastorage/codec/reedsolomon/__init__.py
dnastorage/codec/reedsolomon/rs.py
dnastorage/system/__init__.py
dnastorage/system/dnafile.py
dnastorage/system/formats.py
dnastorage/system/header.py
dnastorage/util/__init__.py
dnastorage/util/neg_binomial_gen.py
dnastorage/util/packetizedfile.py
dnastorage/util/stats.py
dnastorage-0.9.5.dist-info/LICENSE
dnastorage-0.9.5.dist-info/METADATA
dnastorage-0.9.5.dist-info/WHEEL
dnastorage-0.9.5.dist-info/top_level.txt
dnastorage-0.9.5.dist-info/RECORD
