Metadata-Version: 2.1
Name: dnastorage
Version: 0.9.5
Summary: dnastorage provides basic support for encoding and decoding files into and out of DNA with several convenient interfaces.
Home-page: https://github.com/dna-storage/dnastorage
Author: James M. Tuck
Author-email: james.m.tuck@gmail.com
License: UNKNOWN
Platform: UNKNOWN
Classifier: Programming Language :: Python :: 3
Classifier: License :: OSI Approved :: GNU Lesser General Public License v3 (LGPLv3)
Classifier: Operating System :: OS Independent
Classifier: Development Status :: 3 - Alpha
Requires-Python: >=3.6
